odoo/addons/mail_hide_header_portal_button/README.rst
odoo/addons/mail_hide_header_portal_button/__init__.py
odoo/addons/mail_hide_header_portal_button/__manifest__.py
odoo/addons/mail_hide_header_portal_button/data/config_parameter.xml
odoo/addons/mail_hide_header_portal_button/models/__init__.py
odoo/addons/mail_hide_header_portal_button/models/ir_model.py
odoo/addons/mail_hide_header_portal_button/models/mail_thread.py
odoo/addons/mail_hide_header_portal_button/static/description/icon.png
odoo/addons/mail_hide_header_portal_button/tests/__init__.py
odoo/addons/mail_hide_header_portal_button/tests/test_mail_thread.py
odoo_addon_mail_hide_header_portal_button-16.0.1.0.0.dist-info/METADATA
odoo_addon_mail_hide_header_portal_button-16.0.1.0.0.dist-info/WHEEL
odoo_addon_mail_hide_header_portal_button-16.0.1.0.0.dist-info/top_level.txt
odoo_addon_mail_hide_header_portal_button-16.0.1.0.0.dist-info/RECORD
